{
	"name": "untill_activity_filename_sp",
	"properties": {
		"activities": [
			{
				"name": "Until1",
				"type": "Until",
				"dependsOn": [],
				"userProperties": [],
				"typeProperties": {
					"expression": {
						"value": "@equals(variables('fileexist'),true)",
						"type": "Expression"
					},
					"activities": [
						{
							"name": "If Condition1",
							"type": "IfCondition",
							"dependsOn": [
								{
									"activity": "Get Metadata3",
									"dependencyConditions": [
										"Succeeded"
									]
								}
							],
							"userProperties": [],
							"typeProperties": {
								"expression": {
									"value": "@bool(activity('Get Metadata3').output.exists)",
									"type": "Expression"
								},
								"ifFalseActivities": [
									{
										"name": "Wait1",
										"type": "Wait",
										"dependsOn": [],
										"userProperties": [],
										"typeProperties": {
											"waitTimeInSeconds": 120
										}
									}
								],
								"ifTrueActivities": [
									{
										"name": "Set variable1",
										"type": "SetVariable",
										"dependsOn": [],
										"policy": {
											"secureOutput": false,
											"secureInput": false
										},
										"userProperties": [],
										"typeProperties": {
											"variableName": "fileexist",
											"value": "true"
										}
									}
								]
							}
						},
						{
							"name": "Get Metadata3",
							"type": "GetMetadata",
							"dependsOn": [],
							"policy": {
								"timeout": "0.12:00:00",
								"retry": 0,
								"retryIntervalInSeconds": 30,
								"secureOutput": false,
								"secureInput": false
							},
							"userProperties": [],
							"typeProperties": {
								"dataset": {
									"referenceName": "cust_perm",
									"type": "DatasetReference"
								},
								"fieldList": [
									"exists",
									"structure"
								],
								"storeSettings": {
									"type": "AzureBlobFSReadSettings",
									"enablePartitionDiscovery": false
								},
								"formatSettings": {
									"type": "DelimitedTextReadSettings"
								}
							}
						}
					],
					"timeout": "0.00:02:00"
				}
			}
		],
		"variables": {
			"fileexist": {
				"type": "String",
				"defaultValue": "false"
			},
			"customername": {
				"type": "String",
				"defaultValue": "''"
			}
		},
		"annotations": []
	}
}